askgoogle/__init__.py
askgoogle/askgoogle.py
AskGoogle.py-1.0.3.dist-info/LICENSE.txt
AskGoogle.py-1.0.3.dist-info/METADATA
AskGoogle.py-1.0.3.dist-info/WHEEL
AskGoogle.py-1.0.3.dist-info/top_level.txt
AskGoogle.py-1.0.3.dist-info/RECORD
